pyshk/models.py
pyshk/errors.py
pyshk/api.py
pyshk/utils.py
pyshk/__init__.py
pyshk-1.1.0.dist-info/METADATA
pyshk-1.1.0.dist-info/metadata.json
pyshk-1.1.0.dist-info/top_level.txt
pyshk-1.1.0.dist-info/WHEEL
pyshk-1.1.0.dist-info/RECORD
pyshk-1.1.0.dist-info/DESCRIPTION.rst
