Metadata-Version: 2.0
Name: pyshk
Version: 1.1.0
Summary: A python wrapper for the mlkshk API.
Home-page: https://github.com/jeremylow/pyshk
Author: Jeremy Low
Author-email: jeremy@hrhs.co.uk
License: MIT
Keywords: mlkshk pyshk api
Platform: UNKNOWN
Classifier: Development Status :: 4 - Beta
Classifier: License :: OSI Approved :: MIT License
Classifier: Programming Language :: Python :: 2
Classifier: Programming Language :: Python :: 2.7
Classifier: Programming Language :: Python :: 3
Classifier: Programming Language :: Python :: 3.1
Classifier: Programming Language :: Python :: 3.3
Classifier: Programming Language :: Python :: 3.4
Classifier: Programming Language :: Python :: 3.5
Requires-Dist: requests
Requires-Dist: requests-oauthlib
Requires-Dist: requests-toolbelt
Requires-Dist: oauthlib
Requires-Dist: six
